setup.cfg
setup.py
pyexchange/__init__.py
pyexchange/connection.py
pyexchange/exceptions.py
pyexchange/utils.py
pyexchange.egg-info/PKG-INFO
pyexchange.egg-info/SOURCES.txt
pyexchange.egg-info/dependency_links.txt
pyexchange.egg-info/not-zip-safe
pyexchange.egg-info/requires.txt
pyexchange.egg-info/top_level.txt
pyexchange/base/__init__.py
pyexchange/base/calendar.py
pyexchange/base/folder.py
pyexchange/base/soap.py
pyexchange/exchange2010/__init__.py
pyexchange/exchange2010/soap_request.py