Metadata-Version: 1.1
Name: pyexchange
Version: 0.5.1
Summary: A simple library to talk to Microsoft Exchange
Home-page: https://github.com/linkedin/pyexchange
Author: Rachel Sanders
Author-email: rsanders@linkedin.com
License: Apache
Platform: any
Classifier: Development Status :: 3 - Alpha
Classifier: Intended Audience :: Developers
Classifier: License :: OSI Approved :: Apache Software License
Classifier: Operating System :: OS Independent
Classifier: Programming Language :: Python
Classifier: Topic :: Software Development :: Libraries :: Python Modules
